PythonTableConsole/__init__.py
PythonTableConsole/classes.py
PythonTaCo-1.3.7.dist-info/LICENSE
PythonTaCo-1.3.7.dist-info/METADATA
PythonTaCo-1.3.7.dist-info/WHEEL
PythonTaCo-1.3.7.dist-info/top_level.txt
PythonTaCo-1.3.7.dist-info/RECORD
