Metadata-Version: 2.1
Name: PythonTaCo
Version: 1.3.7
Summary: Module for creating tables for console applications
Author-email: Mykhailo Holub <MykhalioHolub@proton.me>
License: MIT License
Project-URL: Homepage, https://github.com/MINIAProgramStudio/PythonTableConsole
Keywords: console,table
Classifier: License :: OSI Approved :: MIT License
Classifier: Programming Language :: Python
Classifier: Programming Language :: Python :: 3
Requires-Python: >=3.10
License-File: LICENSE
Provides-Extra: dev
Requires-Dist: bumpver ; extra == 'dev'
Requires-Dist: pip-tools ; extra == 'dev'
Requires-Dist: pytest ; extra == 'dev'
